search_data_collector/__init__.py
search_data_collector/search_data_collector.py
search_data_collector/search_data_converter.py
search_data_collector/sql_data_collector.py
search_data_collector-0.6.1.dist-info/LICENSE
search_data_collector-0.6.1.dist-info/METADATA
search_data_collector-0.6.1.dist-info/WHEEL
search_data_collector-0.6.1.dist-info/top_level.txt
search_data_collector-0.6.1.dist-info/RECORD
