Metadata-Version: 2.1
Name: search-data-collector
Version: 0.6.1
Author-email: Simon Blanke <simon.blanke@yahoo.com>
Maintainer-email: Simon Blanke <simon.blanke@yahoo.com>
License: MIT License
Project-URL: Homepage, https://github.com/SimonBlanke/search-data-collector
Project-URL: Bug Reports, https://github.com/SimonBlanke/search-data-collector/issues
Project-URL: Source, https://github.com/SimonBlanke/search-data-collector
Keywords: visualization,data-science
Classifier: Programming Language :: Python :: 3
Classifier: Programming Language :: Python :: 3.8
Classifier: License :: OSI Approved :: MIT License
Classifier: Operating System :: OS Independent
Classifier: Topic :: Scientific/Engineering :: Information Analysis
Classifier: Topic :: Scientific/Engineering :: Mathematics
Classifier: Topic :: Software Development :: Libraries :: Python Modules
Classifier: Intended Audience :: Developers
Classifier: Intended Audience :: Information Technology
Classifier: Intended Audience :: Science/Research
Requires-Python: >=3.8
License-File: LICENSE
Requires-Dist: numpy
Requires-Dist: pandas <2.2
Requires-Dist: filelock ==3.13.1
Requires-Dist: sqlalchemy ==1.4.46
Provides-Extra: dev
Requires-Dist: check-manifest ; extra == 'dev'
Provides-Extra: test
Requires-Dist: coverage ; extra == 'test'
